<?xml version="1.0" encoding="UTF-8"?>
<movie id="13387" imdb="tt1129442">
    <title>Transporter 3</title>
    <release>2008</release>
    <tagline>This time, the rules are the same. Except one.</tagline>
    <description>Frank Martin puts the driving gloves on to deliver Valentina, the kidnapped daughter of a Ukranian government official, from Marseilles to Odessa on the Black Sea. En route, he has to contend with thugs who want to intercept Valentina's safe delivery and not let his personal feelings get in the way of his dangerous objective.</description>
    <rating>6.143</rating>
    <poster>
        <image url="/o4w9VF3GRZuXe9NHHvZ07pJespl.jpg" />
    </poster>
    <backdrop>
        <image url="/nNbxrSyKUTMVwpnFgnKH9ZV0QZ8.jpg" />
    </backdrop>
    <categories>
        <category>Action</category> 
<category>Thriller</category> 
<category>Adventure</category> 
<category>Crime</category> 

    </categories>
</movie>

