<?xml version="1.0" encoding="UTF-8"?>
<movie id="616037" imdb="tt10648342">
    <title>Thor Love And Thunder</title>
    <release>2022</release>
    <tagline>The one is not the only.</tagline>
    <description>After his retirement is interrupted by Gorr the God Butcher, a galactic killer who seeks the extinction of the gods, Thor Odinson enlists the help of King Valkyrie, Korg, and ex-girlfriend Jane Foster, who now wields Mjolnir as the Mighty Thor. Together they embark upon a harrowing cosmic adventure to uncover the mystery of the God Butcher’s vengeance and stop him before it’s too late.</description>
    <rating>6.5</rating>
    <poster>
        <image url="/pIkRyD18kl4FhoCNQuWxWu5cBLM.jpg" />
    </poster>
    <backdrop>
        <image url="/jsoz1HlxczSuTx0mDl2h0lxy36l.jpg" />
    </backdrop>
    <categories>
        <category>Action</category> 
<category>Comedy</category> 
<category>Fantasy</category> 

    </categories>
</movie>

